ninjaprinter/__init__.py
ninjaprinter/mailbox.py
ninjaprinter/printer.py
ninjaprinter/processor.py
ninjaprinter/templates/base.html
ninjaprinter/templates/content.html
ninjaprinter/templates/error.html
ninjaprinter/templates/partial.html
ninjaprinter/templates/subject.txt
ninjaprinter/templates/success.html
ninjaprinter-0.9.4.dist-info/LICENSE
ninjaprinter-0.9.4.dist-info/METADATA
ninjaprinter-0.9.4.dist-info/WHEEL
ninjaprinter-0.9.4.dist-info/top_level.txt
ninjaprinter-0.9.4.dist-info/RECORD
